textual_filelink-0.10.1.dist-info/METADATA
textual_filelink-0.10.1.dist-info/WHEEL
textual_filelink-0.10.1.dist-info/entry_points.txt
textual_filelink-0.10.1.dist-info/licenses/LICENSE
textual_filelink/__init__.py
textual_filelink/command_link.py
textual_filelink/file_link.py
textual_filelink/file_link_list.py
textual_filelink/file_link_with_icons.py
textual_filelink/icon.py
textual_filelink/logging.py
textual_filelink/utils.py
textual_filelink-0.10.1.dist-info/RECORD
