Metadata-Version: 2.1
Name: textual-filelink
Version: 0.10.1
Summary: Clickable file links with icons, toggles, and command orchestration widget for Textual TUI applications.
Keywords: textual,tui,terminal,file,link,widget,clickable,file-manager,developer-tools,command-runner,keyboard-navigation
Author-Email: eyecantell <paul@pneuma.solutions>
License: MIT
Classifier: Development Status :: 4 - Beta
Classifier: Environment :: Console
Classifier: Intended Audience :: Developers
Classifier: License :: OSI Approved :: MIT License
Classifier: Operating System :: OS Independent
Classifier: Programming Language :: Python :: 3
Classifier: Programming Language :: Python :: 3.9
Classifier: Programming Language :: Python :: 3.10
Classifier: Programming Language :: Python :: 3.11
Classifier: Programming Language :: Python :: 3.12
Classifier: Programming Language :: Python :: 3.13
Classifier: Topic :: Software Development :: Libraries :: Python Modules
Classifier: Topic :: Terminals
Classifier: Topic :: Software Development :: User Interfaces
Project-URL: Homepage, https://github.com/eyecantell/textual-filelink
Project-URL: Repository, https://github.com/eyecantell/textual-filelink
Project-URL: Issues, https://github.com/eyecantell/textual-filelink/issues
Project-URL: Documentation, https://github.com/eyecantell/textual-filelink#readme
Project-URL: Changelog, https://github.com/eyecantell/textual-filelink/releases
Requires-Python: >=3.9
Requires-Dist: textual>=6.11.0
Provides-Extra: dev
Requires-Dist: pytest>=7.4.4; extra == "dev"
Requires-Dist: pytest-asyncio>=0.21.0; extra == "dev"
Requires-Dist: pytest-cov>=4.0.0; extra == "dev"
Requires-Dist: ruff>=0.1.0; extra == "dev"
Requires-Dist: mypy>=1.0.0; extra == "dev"
Requires-Dist: textual-dev>=1.8.0; extra == "dev"
Requires-Dist: textual-capture>=0.3.0; extra == "dev"
